pyadb/__init__.py
pyadb/common.py
pyadb/adb/__init__.py
pyadb/adb/sub_command/__init__.py
pyadb/adb/sub_command/base.py
pyadb/adb/sub_command/forward.py
pyadb/adb/sub_command/logcat.py
pyadb/adb/sub_command/mapping.py
pyadb/adb/sub_command/reverse.py
pyadb/demo/__init__.py
pyadb/device/__init__.py
pyadb/device/helper/__init__.py
pyadb/device/helper/app.py
pyadb/device/helper/base.py
pyadb/device/helper/display.py
pyadb/device/helper/file.py
pyadb/device/helper/input.py
pyadb/utils/__init__.py
pyadb/utils/shell_lib.py
OjoPyADB-0.2.0.dist-info/LICENSE
OjoPyADB-0.2.0.dist-info/METADATA
OjoPyADB-0.2.0.dist-info/WHEEL
OjoPyADB-0.2.0.dist-info/top_level.txt
OjoPyADB-0.2.0.dist-info/RECORD
