Metadata-Version: 2.1
Name: OjoPyADB
Version: 0.2.0
Summary: HsOjo's Python3 Android Debug Bridge. Support App/File/Input/Display Operation...
Home-page: https://github.com/HsOjo/OjoPyADB/
Author: HsOjo
Author-email: hsojo@qq.com
License: UNKNOWN
Keywords: hsojo python3 android adb pyadb ojopyadb
Platform: UNKNOWN
Classifier: Programming Language :: Python :: 3
Classifier: License :: OSI Approved :: MIT License
Classifier: Operating System :: OS Independent
Requires-Python: >=3.6
